dnd_5e_core/__init__.py
dnd_5e_core/abilities/__init__.py
dnd_5e_core/abilities/abilities.py
dnd_5e_core/abilities/saving_throw.py
dnd_5e_core/abilities/skill.py
dnd_5e_core/classes/__init__.py
dnd_5e_core/classes/class_type.py
dnd_5e_core/classes/multiclass.py
dnd_5e_core/classes/proficiency.py
dnd_5e_core/combat/__init__.py
dnd_5e_core/combat/action.py
dnd_5e_core/combat/combat_system.py
dnd_5e_core/combat/condition.py
dnd_5e_core/combat/damage.py
dnd_5e_core/combat/special_ability.py
dnd_5e_core/data/__init__.py
dnd_5e_core/data/api_client.py
dnd_5e_core/data/collections.py
dnd_5e_core/data/loader.py
dnd_5e_core/data/loaders.py
dnd_5e_core/data/serialization.py
dnd_5e_core/data/monsters/README.md
dnd_5e_core/data/monsters/bestiary-sublist-data-all-monsters.json
dnd_5e_core/data/monsters/bestiary-sublist-data.json
dnd_5e_core/entities/__init__.py
dnd_5e_core/entities/character.py
dnd_5e_core/entities/extended_monsters.py
dnd_5e_core/entities/monster.py
dnd_5e_core/entities/special_monster_actions.py
dnd_5e_core/entities/sprite.py
dnd_5e_core/equipment/__init__.py
dnd_5e_core/equipment/armor.py
dnd_5e_core/equipment/equipment.py
dnd_5e_core/equipment/inventory.py
dnd_5e_core/equipment/magic_item.py
dnd_5e_core/equipment/potion.py
dnd_5e_core/equipment/predefined_magic_items.py
dnd_5e_core/equipment/weapon.py
dnd_5e_core/mechanics/__init__.py
dnd_5e_core/mechanics/challenge_rating.py
dnd_5e_core/mechanics/dice.py
dnd_5e_core/mechanics/encounter_builder.py
dnd_5e_core/mechanics/experience.py
dnd_5e_core/mechanics/gold_rewards.py
dnd_5e_core/mechanics/level_up.py
dnd_5e_core/races/__init__.py
dnd_5e_core/races/language.py
dnd_5e_core/races/race.py
dnd_5e_core/races/subrace.py
dnd_5e_core/races/trait.py
dnd_5e_core/spells/__init__.py
dnd_5e_core/spells/cantrips.py
dnd_5e_core/spells/spell.py
dnd_5e_core/spells/spell_slots.py
dnd_5e_core/spells/spellcaster.py
dnd_5e_core/ui/__init__.py
dnd_5e_core/utils/__init__.py
dnd_5e_core/utils/constants.py
dnd_5e_core-0.2.2.dist-info/licenses/LICENSE
dnd_5e_core-0.2.2.dist-info/METADATA
dnd_5e_core-0.2.2.dist-info/WHEEL
dnd_5e_core-0.2.2.dist-info/top_level.txt
dnd_5e_core-0.2.2.dist-info/RECORD
