Metadata-Version: 2.4
Name: dnd-5e-core
Version: 0.2.2
Summary: Complete D&D 5e Rules Engine with Magic Items, Defensive Spells & Conditions: 332 monsters, 319+ spells, combat conditions, treasure system. 100% offline.
Home-page: https://github.com/codingame-team/dnd-5e-core
Author: D&D Development Team
Author-email: D&D Development Team <dev@codingame-team.com>
Maintainer-email: D&D Development Team <dev@codingame-team.com>
License: MIT
Project-URL: Homepage, https://github.com/codingame-team/dnd-5e-core
Project-URL: Documentation, https://github.com/codingame-team/dnd-5e-core/blob/main/README.md
Project-URL: Repository, https://github.com/codingame-team/dnd-5e-core
Project-URL: Source Code, https://github.com/codingame-team/dnd-5e-core
Project-URL: Issues, https://github.com/codingame-team/dnd-5e-core/issues
Project-URL: Bug Tracker, https://github.com/codingame-team/dnd-5e-core/issues
Project-URL: Changelog, https://github.com/codingame-team/dnd-5e-core/blob/main/CHANGELOG.md
Project-URL: Quick Start, https://github.com/codingame-team/dnd-5e-core/blob/main/QUICK_START_DATA.md
Project-URL: Examples & Demos, https://github.com/codingame-team/DND5e-Test
Project-URL: Full Applications, https://github.com/codingame-team/DnD-5th-Edition-API
Keywords: dnd,dungeons-dragons,d&d,5e,rpg,tabletop,game-engine,character-sheet,combat-engine,spells,monsters,encounter-builder,dmg,challenge-rating,gold-rewards,standalone,offline
Classifier: Development Status :: 3 - Alpha
Classifier: Intended Audience :: Developers
Classifier: Intended Audience :: End Users/Desktop
Classifier: License :: OSI Approved :: MIT License
Classifier: Natural Language :: English
Classifier: Operating System :: OS Independent
Classifier: Programming Language :: Python :: 3
Classifier: Programming Language :: Python :: 3.10
Classifier: Programming Language :: Python :: 3.11
Classifier: Programming Language :: Python :: 3.12
Classifier: Programming Language :: Python :: 3.13
Classifier: Programming Language :: Python :: 3 :: Only
Classifier: Topic :: Games/Entertainment :: Role-Playing
Classifier: Topic :: Games/Entertainment :: Turn Based Strategy
Classifier: Topic :: Software Development :: Libraries :: Python Modules
Classifier: Typing :: Typed
Requires-Python: >=3.10
License-File: LICENSE
Requires-Dist: numpy>=1.20.0
Requires-Dist: requests>=2.28.0
Provides-Extra: dev
Requires-Dist: pytest>=7.0; extra == "dev"
Requires-Dist: pytest-cov>=3.0; extra == "dev"
Requires-Dist: black>=22.0; extra == "dev"
Requires-Dist: mypy>=0.950; extra == "dev"
Requires-Dist: flake8>=4.0; extra == "dev"
Requires-Dist: requests-mock>=1.9.3; extra == "dev"
Dynamic: author
Dynamic: home-page
Dynamic: license-file
Dynamic: requires-python
